zoom_background_changer/__init__.py
zoom_background_changer/main.py
zoom_background_changer-0.2.0.dist-info/entry_points.txt
zoom_background_changer-0.2.0.dist-info/WHEEL
zoom_background_changer-0.2.0.dist-info/METADATA
zoom_background_changer-0.2.0.dist-info/RECORD
