Metadata-Version: 2.1
Name: zoom-background-changer
Version: 0.2.0
Summary: Changes your Zoom background using OpenAI Image Generation.
Author: Kyle Montag
Author-email: thekylemontag@gmail.com
Requires-Python: >=3.9,<4.0
Classifier: Programming Language :: Python :: 3
Classifier: Programming Language :: Python :: 3.9
Classifier: Programming Language :: Python :: 3.10
Requires-Dist: openai (>=0.27.4,<0.28.0)
